src/__init__.py
src/api.py
src/cli.py
neorcli-3.12.6.dist-info/LICENSE
neorcli-3.12.6.dist-info/METADATA
neorcli-3.12.6.dist-info/WHEEL
neorcli-3.12.6.dist-info/entry_points.txt
neorcli-3.12.6.dist-info/top_level.txt
neorcli-3.12.6.dist-info/RECORD
