Metadata-Version: 2.1
Name: neorcli
Version: 3.12.6
Summary: NeorCli tool
Home-page: https://github.com/NeorCloud/neor-cli
Author: Ali Ghotbizadeh
Author-email: ali.ghotbizadeh@gmail.com
License: MIT
Keywords: NeorCloud NeorCli
Platform: UNKNOWN
Classifier: Programming Language :: Python :: 3
Classifier: Programming Language :: Python :: 3 :: Only
Classifier: Programming Language :: Python :: 3.7
Classifier: Programming Language :: Python :: 3.8
Classifier: Programming Language :: Python :: 3.9
Classifier: Programming Language :: Python :: 3.10
Classifier: Programming Language :: Python :: 3.11
Classifier: License :: OSI Approved :: MIT License
Classifier: Operating System :: OS Independent
Requires-Python: >=3.7, <3.12
License-File: LICENSE
Requires-Dist: aiodns (==3.0.0)
Requires-Dist: aiohttp[speedups] (==3.8.3)
Requires-Dist: aiosignal (==1.3.1)
Requires-Dist: async-timeout (==4.0.2)
Requires-Dist: attrs (==22.1.0)
Requires-Dist: brotli (==1.0.9)
Requires-Dist: cffi (==1.15.1)
Requires-Dist: charset-normalizer (==2.1.1)
Requires-Dist: frozenlist (==1.3.3)
Requires-Dist: humanize (==4.4.0)
Requires-Dist: idna (==3.4)
Requires-Dist: multidict (==6.0.3)
Requires-Dist: pycares (==4.3.0)
Requires-Dist: pycparser (==2.21)
Requires-Dist: pyyaml (==6.0)
Requires-Dist: tabulate (==0.9.0)
Requires-Dist: yarl (==1.8.2)
